chatbot_builder/__init__.py
chatbot_builder/bot_builder.py
chatbot_builder/bot_builder_cli.py
chatbot_builder/constants.py
chatbot_builder/clients/__init__.py
chatbot_builder/clients/discord_bot.py
chatbot_builder/clients/discord_client.py
chatbot_builder-0.5.0.dist-info/DESCRIPTION.rst
chatbot_builder-0.5.0.dist-info/METADATA
chatbot_builder-0.5.0.dist-info/RECORD
chatbot_builder-0.5.0.dist-info/WHEEL
chatbot_builder-0.5.0.dist-info/metadata.json
chatbot_builder-0.5.0.dist-info/top_level.txt
