Metadata-Version: 2.0
Name: chatbot-builder
Version: 0.5.0
Summary: A discord chatbot that is programmed interactively by discord users
Home-page: http://github.com/eriknyquist/deep_space_trader
Author: Erik Nyquist
Author-email: eknyquist@gmail.com
License: Apache 2.0
Platform: UNKNOWN
Requires-Dist: chatbot-utils
Requires-Dist: discord
Requires-Dist: wheel
